auto_privacy_audit/__init__.py
auto_privacy_audit/analyzer.py
auto_privacy_audit-0.1.2.dist-info/METADATA
auto_privacy_audit-0.1.2.dist-info/WHEEL
auto_privacy_audit-0.1.2.dist-info/top_level.txt
auto_privacy_audit-0.1.2.dist-info/RECORD
