Metadata-Version: 2.2
Name: auto_privacy_audit
Version: 0.1.2
Summary: 自动隐私合规检测器：基于 AST 的静态代码分析工具，帮助检测代码中的敏感信息泄露风险
Home-page: https://github.com/Yantha6/AutoPrivacyAudit
Author: yangtianhan
Author-email: 1257330051@qq.com
Classifier: Programming Language :: Python :: 3
Classifier: License :: OSI Approved :: MIT License
Classifier: Operating System :: OS Independent
Requires-Python: >=3.6
Dynamic: author
Dynamic: author-email
Dynamic: classifier
Dynamic: description
Dynamic: description-content-type
Dynamic: home-page
Dynamic: requires-python
Dynamic: summary
